{
  "generated_at": "2026-04-27T09:24:25Z",
  "available": true,
  "dimension": "seniority",
  "items": [
    {
      "key": "senior",
      "label": "senior",
      "vacancy_count": 2728,
      "share": 0.5011
    },
    {
      "key": "manager",
      "label": "manager",
      "vacancy_count": 1242,
      "share": 0.2281
    },
    {
      "key": "mid",
      "label": "mid",
      "vacancy_count": 624,
      "share": 0.1146
    },
    {
      "key": "junior",
      "label": "junior",
      "vacancy_count": 395,
      "share": 0.0726
    },
    {
      "key": "Unknown",
      "label": "Unknown",
      "vacancy_count": 346,
      "share": 0.0636
    },
    {
      "key": "intern",
      "label": "intern",
      "vacancy_count": 109,
      "share": 0.02
    }
  ]
}
