{
  "generated_at": "2026-05-31T16:16:42Z",
  "available": true,
  "dimension": "work_mode",
  "items": [
    {
      "key": "Unknown",
      "label": "Unknown",
      "vacancy_count": 3018,
      "share": 0.5826
    },
    {
      "key": "hybrid",
      "label": "hybrid",
      "vacancy_count": 1163,
      "share": 0.2245
    },
    {
      "key": "onsite",
      "label": "onsite",
      "vacancy_count": 642,
      "share": 0.1239
    },
    {
      "key": "remote",
      "label": "remote",
      "vacancy_count": 357,
      "share": 0.0689
    }
  ]
}
