{
  "generated_at": "2026-04-23T10:13:54Z",
  "available": true,
  "dimension": "work_mode",
  "items": [
    {
      "key": "Unknown",
      "label": "Unknown",
      "vacancy_count": 6954,
      "share": 0.674
    },
    {
      "key": "hybrid",
      "label": "hybrid",
      "vacancy_count": 1915,
      "share": 0.1856
    },
    {
      "key": "remote",
      "label": "remote",
      "vacancy_count": 815,
      "share": 0.079
    },
    {
      "key": "onsite",
      "label": "onsite",
      "vacancy_count": 634,
      "share": 0.0614
    }
  ]
}
